paperswithcode/__init__.py
paperswithcode/__main__.py
paperswithcode/client.py
paperswithcode/config.py
paperswithcode/consts.py
paperswithcode/errors.py
paperswithcode/version.py
paperswithcode/commands/__init__.py
paperswithcode/commands/app.py
paperswithcode/models/__init__.py
paperswithcode/models/author.py
paperswithcode/models/conference.py
paperswithcode/models/dataset.py
paperswithcode/models/method.py
paperswithcode/models/page.py
paperswithcode/models/paper.py
paperswithcode/models/paper_repo.py
paperswithcode/models/repository.py
paperswithcode/models/task.py
paperswithcode/models/evaluation/__init__.py
paperswithcode/models/evaluation/metric.py
paperswithcode/models/evaluation/result.py
paperswithcode/models/evaluation/synchronize.py
paperswithcode/models/evaluation/table.py
paperswithcode_client-0.3.1.dist-info/LICENSE
paperswithcode_client-0.3.1.dist-info/METADATA
paperswithcode_client-0.3.1.dist-info/WHEEL
paperswithcode_client-0.3.1.dist-info/entry_points.txt
paperswithcode_client-0.3.1.dist-info/top_level.txt
paperswithcode_client-0.3.1.dist-info/RECORD
