Metadata-Version: 2.1
Name: paperswithcode-client
Version: 0.3.1
Summary: Python client for paperswithcode.com API.
Home-page: https://github.com/paperswithcode/paperswithcode-client
Author: Viktor Kerkez
Author-email: alefnula@gmail.com
Maintainer: Viktor Kerkez
Maintainer-email: alefnula@gmail.com
License: Apache-2.0
Platform: Windows
Platform: POSIX
Platform: MacOSX
License-File: LICENSE
